csmdirsearch/__init__.py
csmdirsearch/__main__.py
csmdirsearch/dirsearch.py
csmdirsearch-0.1.1.dist-info/LICENSE
csmdirsearch-0.1.1.dist-info/METADATA
csmdirsearch-0.1.1.dist-info/WHEEL
csmdirsearch-0.1.1.dist-info/entry_points.txt
csmdirsearch-0.1.1.dist-info/top_level.txt
csmdirsearch-0.1.1.dist-info/RECORD
