Metadata-Version: 2.1
Name: csmdirsearch
Version: 0.1.1
Summary: Search the Mines directory
Home-page: https://github.com/jackrosenthal/csmdirsearch
Author: Jack Rosenthal, Samuel Warfield
Author-email: warfield@mines.edu
License: MIT
Keywords: directory mines scraping
Platform: UNKNOWN
Classifier: Development Status :: 3 - Alpha
Classifier: Intended Audience :: Education
Classifier: Topic :: System :: Systems Administration :: Authentication/Directory
Classifier: License :: OSI Approved :: MIT License
Classifier: Programming Language :: Python :: 3
Classifier: Programming Language :: Python :: 3.7
Requires-Python: >=3.7, <7
Requires-Dist: beautifulsoup4 (>=4.4.0)
Requires-Dist: requests (>=2.0.0)
